mgtoolbox_kernel/__init__.py
mgtoolbox_kernel/crystal_tools/__init__.py
mgtoolbox_kernel/crystal_tools/crystal_symmetry.py
mgtoolbox_kernel/io/__init__.py
mgtoolbox_kernel/io/cif.py
mgtoolbox_kernel/io/vasp/__init__.py
mgtoolbox_kernel/io/vasp/poscar.py
mgtoolbox_kernel/kernel/__init__.py
mgtoolbox_kernel/kernel/atom.py
mgtoolbox_kernel/kernel/cell.py
mgtoolbox_kernel/kernel/mgclass.py
mgtoolbox_kernel/kernel/potential.py
mgtoolbox_kernel/kernel/site.py
mgtoolbox_kernel/kernel/structure.py
mgtoolbox_kernel/util/__init__.py
mgtoolbox_kernel/util/base.py
mgtoolbox_kernel-0.1.2.dist-info/METADATA
mgtoolbox_kernel-0.1.2.dist-info/WHEEL
mgtoolbox_kernel-0.1.2.dist-info/top_level.txt
mgtoolbox_kernel-0.1.2.dist-info/RECORD
