Metadata-Version: 2.1
Name: mgtoolbox-kernel
Version: 0.1.2
Home-page: https://gitee.com/shuhebing/mgtoolbox_kernel
Author: Bing He
Author-email: shhebing@qq.com
Requires-Python: >=3.7,<=3.12
Requires-Dist: pycifrw
Requires-Dist: numpy
Requires-Dist: scipy
Requires-Dist: pandas
Requires-Dist: spglib
